{
  "parent": "minecraft:block/block",
  "textures": {
    "side": "betterthanwolves:block/fcblockbucketempty_top_side",
    "top": "betterthanwolves:block/fcblockbucketempty_top",
    "bottom": "betterthanwolves:block/fcblockbucketempty_top",
    "front": "betterthanwolves:block/fcblockbucketempty_top_side",
    "particle": "betterthanwolves:block/fcblockbucketempty"
  },
  "elements": [
    {
      "from": [5.0, 0.0, 5.0],
      "to": [11.0, 1.0, 11.0],
      "faces": {
        "north": {"texture": "#front"},
        "south": {"texture": "#side"},
        "east": {"texture": "#side"},
        "west": {"texture": "#side"},
        "up": {"texture": "#top"},
        "down": {"texture": "#bottom"}
      }
    },
    {
      "from": [4.5, 1.0, 4.5],
      "to": [11.5, 7.0, 11.5],
      "faces": {
        "north": {"texture": "#front"},
        "south": {"texture": "#side"},
        "east": {"texture": "#side"},
        "west": {"texture": "#side"},
        "up": {"texture": "#top"},
        "down": {"texture": "#bottom"}
      }
    },
    {
      "from": [4.0, 7.0, 4.0],
      "to": [12.0, 8.0, 12.0],
      "faces": {
        "north": {"texture": "#front"},
        "south": {"texture": "#side"},
        "east": {"texture": "#side"},
        "west": {"texture": "#side"},
        "up": {"texture": "#top"},
        "down": {"texture": "#bottom"}
      }
    },
    {
      "from": [11.0, 8.0, 11.0],
      "to": [5.0, 2.5, 5.0],
      "faces": {
        "north": {"texture": "#front"},
        "south": {"texture": "#side"},
        "east": {"texture": "#side"},
        "west": {"texture": "#side"},
        "up": {"texture": "#top"},
        "down": {"texture": "#bottom"}
      }
    }
  ]
}