{
  "variants": {"meta=0": {"model": "betterthanwolves:block/fcblockbellows"}, "meta=1": {"model": "betterthanwolves:block/fcblockbellows"}, "meta=2": {"model": "betterthanwolves:block/fcblockbellows"}, "meta=3": {"model": "betterthanwolves:block/fcblockbellows"}, "meta=4": {"model": "betterthanwolves:block/fcblockbellows"}, "meta=5": {"model": "betterthanwolves:block/fcblockbellows"}, "meta=6": {"model": "betterthanwolves:block/fcblockbellows"}, "meta=7": {"model": "betterthanwolves:block/fcblockbellows"}, "meta=8": {"model": "betterthanwolves:block/fcblockbellows"}, "meta=9": {"model": "betterthanwolves:block/fcblockbellows"}, "meta=10": {"model": "betterthanwolves:block/fcblockbellows"}, "meta=11": {"model": "betterthanwolves:block/fcblockbellows"}, "meta=12": {"model": "betterthanwolves:block/fcblockbellows"}, "meta=13": {"model": "betterthanwolves:block/fcblockbellows"}, "meta=14": {"model": "betterthanwolves:block/fcblockbellows"}, "meta=15": {"model": "betterthanwolves:block/fcblockbellows"}}
}